mh_utils-0.2.2.dist-info/WHEEL
mh_utils-0.2.2.dist-info/top_level.txt
mh_utils-0.2.2.dist-info/entry_points.txt
mh_utils-0.2.2.dist-info/METADATA
mh_utils-0.2.2.dist-info/LICENSE
mh_utils/pcdl.py
mh_utils/utils.py
mh_utils/py.typed
mh_utils/__init__.py
mh_utils/xml.py
mh_utils/cef_parser/__init__.py
mh_utils/csv_parser/utils.py
mh_utils/csv_parser/__init__.py
mh_utils/csv_parser/classes.py
mh_utils/worklist_parser/columns.py
mh_utils/worklist_parser/__init__.py
mh_utils/worklist_parser/parser.py
mh_utils/worklist_parser/enums.py
mh_utils/worklist_parser/classes.py
