Metadata-Version: 2.1
Name: mh-utils
Version: 0.2.2
Summary: Utilities for handing ancillary files produced by MassHunter.
Author-email: Dominic Davis-Foster <dominic@davis-foster.co.uk>
License: LGPL-3.0-or-later
Keywords: chemistry,chromatography,mass-spectrometry
Home-page: https://github.com/domdfcoding/mh_utils
Project-URL: Issue Tracker, https://github.com/domdfcoding/mh_utils/issues
Project-URL: Source Code, https://github.com/domdfcoding/mh_utils
Project-URL: Documentation, https://mh_utils.readthedocs.io/en/latest
Platform: Windows
Platform: macOS
Platform: Linux
Classifier: Intended Audience :: Developers
Classifier: License :: OSI Approved :: GNU Lesser General Public License v3 or later (LGPLv3+)
Classifier: Operating System :: OS Independent
Classifier: Programming Language :: Python
Classifier: Programming Language :: Python :: 3 :: Only
Classifier: Programming Language :: Python :: 3.6
Classifier: Programming Language :: Python :: 3.7
Classifier: Programming Language :: Python :: 3.8
Classifier: Programming Language :: Python :: 3.9
Classifier: Programming Language :: Python :: Implementation :: CPython
Classifier: Topic :: Software Development :: Libraries :: Python Modules
Classifier: Typing :: Typed
Requires-Python: >=3.6
Requires-Dist: attr-utils>=0.5.4
Requires-Dist: attrs>=20.2.0
Requires-Dist: cawdrey>=0.2.0
Requires-Dist: chemistry-tools[formulae]>=0.4.0
Requires-Dist: domdf-python-tools>=2.0.1
Requires-Dist: enum-tools>=0.6.1
Requires-Dist: lxml>=4.6.0
Requires-Dist: numpy>=1.19.4; platform_system != "Windows"
Requires-Dist: numpy!=1.19.4,<1.20,>=1.19.3; platform_system == "Windows"
Requires-Dist: pandas>=1.1.3
Requires-Dist: sdjson>=0.3.0
Requires-Dist: typing-extensions>=3.7.4.3
